ipyleaflet/__init__.py
ipyleaflet/_version.py
ipyleaflet/basemaps.py
ipyleaflet/leaflet.py
ipyleaflet/projections.py
ipyleaflet/velocity.py
ipyleaflet/xarray_ds.py
ipyleaflet/external/__init__.py
ipyleaflet/external/here.py
ipyleaflet_bis-0.20.4.dist-info/METADATA
ipyleaflet_bis-0.20.4.dist-info/WHEEL
ipyleaflet_bis-0.20.4.dist-info/licenses/LICENSE
ipyleaflet_bis-0.20.4.dist-info/RECORD
