Metadata-Version: 2.4
Name: ipyleaflet-bis
Version: 0.20.4
Summary: A Jupyter widget for dynamic Leaflet maps
Project-URL: Homepage, https://github.com/jupyter-widgets/ipyleaflet
Author-email: Project Jupyter <jupyter@googlegroups.com>
License: The MIT License (MIT)
License-File: LICENSE
Keywords: GIS,graphics,ipython,jupyter,widgets
Classifier: Intended Audience :: Developers
Classifier: Intended Audience :: Science/Research
Classifier: License :: OSI Approved :: MIT License
Classifier: Programming Language :: Python :: 3.8
Classifier: Programming Language :: Python :: 3.9
Classifier: Programming Language :: Python :: 3.10
Classifier: Programming Language :: Python :: 3.11
Classifier: Programming Language :: Python :: 3.12
Classifier: Topic :: Multimedia :: Graphics
Requires-Python: >=3.8
Requires-Dist: branca>=0.5.0
Requires-Dist: ipywidgets<9,>=7.6.0
Requires-Dist: jupyter-leaflet-bis<0.21,>=0.20
Requires-Dist: traittypes<3,>=0.2.1
Requires-Dist: xyzservices>=2021.8.1
